dsmscp/__init__.py
dsmscp/__main__.py
dsmscp/dscpdev.py
dsmscp/app/__init__.py
dsmscp/app/common.py
dsmscp/app/conf.txt
dsmscp/app/launcher.py
dsmscp/app/utils.py
dsmscp/app/gui/DialogComPort.py
dsmscp/app/gui/MainWindow.py
dsmscp/app/gui/__init__.py
dsmscp/app/gui/guiapp.py
dsmscp/app/gui/ui_dialogcomport.py
dsmscp/app/gui/ui_mainwindow.py
dsmscp/app/listener/Listener.py
dsmscp/app/listener/__init__.py
dsmscp/img/autorefresh.svg
dsmscp/img/dassym-icon.png
dsmscp/img/dot-green.svg
dsmscp/img/dot-red.svg
dsmscp-0.1.1.dist-info/LICENSE
dsmscp-0.1.1.dist-info/METADATA
dsmscp-0.1.1.dist-info/WHEEL
dsmscp-0.1.1.dist-info/top_level.txt
dsmscp-0.1.1.dist-info/RECORD
