Metadata-Version: 2.1
Name: dsmscp
Version: 0.1.1
Summary: The dsmscp application offer a simple way to debug dassym motor.
Home-page: https://github.com/dassym/dsmscp
Author: Tom Marti
Author-email: dev@dassym.com
License: UNKNOWN
Keywords: Dassym,motor,api,dapi
Platform: UNKNOWN
Classifier: Programming Language :: Python :: 3
Classifier: Operating System :: OS Independent
Requires-Python: >=3.8
Requires-Dist: PyDapi2
Requires-Dist: PyQt5
Requires-Dist: pyserial
Requires-Dist: chardet
